singleparticle/__init__.py
singleparticle/bibtex.py
singleparticle/constants.py
singleparticle/convert.py
singleparticle/icon.png
singleparticle/protocols.conf
singleparticle/_vendored/TiPi/.gitignore
singleparticle/_vendored/TiPi/LICENSE.md
singleparticle/_vendored/TiPi/NEWS.md
singleparticle/_vendored/TiPi/README.md
singleparticle/_vendored/TiPi/TODO.md
singleparticle/_vendored/TiPi/mkdocs.yml
singleparticle/_vendored/TiPi/pom.xml
singleparticle/_vendored/TiPi/settings.xml
singleparticle/_vendored/TiPi/docs/array-factory.md
singleparticle/_vendored/TiPi/docs/deconv-tool.md
singleparticle/_vendored/TiPi/docs/devel.md
singleparticle/_vendored/TiPi/docs/framework.md
singleparticle/_vendored/TiPi/docs/index.md
singleparticle/_vendored/TiPi/docs/license.md
singleparticle/_vendored/TiPi/docs/new-vector-types.md
singleparticle/_vendored/TiPi/docs/news.md
singleparticle/_vendored/TiPi/docs/shaped-arrays.md
singleparticle/_vendored/TiPi/docs/todo.md
singleparticle/_vendored/TiPi/docs/tpp.md
singleparticle/_vendored/TiPi/docs/vectors.md
singleparticle/_vendored/TiPi/src/main/java/commands/BlindDeconvolutionCommand.java
singleparticle/_vendored/TiPi/src/main/java/commands/EdgePreservingDeconvolutionCommand.java
singleparticle/_vendored/TiPi/src/main/java/commands/MainCommand.java
singleparticle/_vendored/TiPi/src/main/java/org/mitiv/TiPi/array/Array1D.java
singleparticle/_vendored/TiPi/src/main/java/org/mitiv/TiPi/array/Array2D.java
singleparticle/_vendored/TiPi/src/main/java/org/mitiv/TiPi/array/Array3D.java
singleparticle/_vendored/TiPi/src/main/java/org/mitiv/TiPi/array/Array4D.java
singleparticle/_vendored/TiPi/src/main/java/org/mitiv/TiPi/array/Array5D.java
singleparticle/_vendored/TiPi/src/main/java/org/mitiv/TiPi/array/Array6D.java
singleparticle/_vendored/TiPi/src/main/java/org/mitiv/TiPi/array/Array7D.java
singleparticle/_vendored/TiPi/src/main/java/org/mitiv/TiPi/array/Array8D.java
singleparticle/_vendored/TiPi/src/main/java/org/mitiv/TiPi/array/Array9D.java
scipion_fluo_singleparticle-0.1.0.dist-info/METADATA
scipion_fluo_singleparticle-0.1.0.dist-info/WHEEL
scipion_fluo_singleparticle-0.1.0.dist-info/entry_points.txt
scipion_fluo_singleparticle-0.1.0.dist-info/licenses/LICENSE
scipion_fluo_singleparticle-0.1.0.dist-info/RECORD
