Metadata-Version: 2.3
Name: scipion-fluo-singleparticle
Version: 0.1.0
Summary: Scipion plugin for single particle reconstruction.
Project-URL: Repository, https://github.com/jplumail/scipion-fluo-singleparticle
Author-email: Jean Plumail <jplumail@unistra.fr>
Keywords: fluorescence,imageprocessing,scipion,scipion-3.0
Requires-Dist: flask
Requires-Dist: napari-spfluo
Requires-Dist: numpy
Requires-Dist: scipion-fluo
Requires-Dist: scipion-pyworkflow-windows
Requires-Dist: scipy
Requires-Dist: spfluo[ab-initio-reconstruction,manual-picking,picking,visualisation]
Requires-Dist: waitress
